terraform_external_data/__init__.py
terraform_external_data/terraform_external_data.py
terraform_external_data-1.0.3.dist-info/AUTHORS.txt
terraform_external_data-1.0.3.dist-info/LICENSE.txt
terraform_external_data-1.0.3.dist-info/METADATA
terraform_external_data-1.0.3.dist-info/WHEEL
terraform_external_data-1.0.3.dist-info/top_level.txt
terraform_external_data-1.0.3.dist-info/RECORD
