Metadata-Version: 2.1
Name: terraform-external-data
Version: 1.0.3
Summary: Terraform external data package
Home-page: https://github.com/juozaskibildis-zt/terraform_external_data
Author: Juozas Kibildis
Author-email: juozas.kibildis@zenitech.co.uk
License: UNKNOWN
Project-URL: Bug Tracker, https://github.com/juozaskibildis-zt/terraform_external_data/issues
Platform: UNKNOWN
Classifier: Programming Language :: Python :: 3
Classifier: License :: OSI Approved :: MIT License
Classifier: Operating System :: OS Independent
Requires-Python: >=3.6
License-File: LICENSE.txt
License-File: AUTHORS.txt
